pynspd/__init__.py
pynspd/cli.py
pynspd/client.py
pynspd/errors.py
pynspd/logger.py
pynspd/py.typed
pynspd/_async/__init__.py
pynspd/_async/api.py
pynspd/_sync/__init__.py
pynspd/_sync/api.py
pynspd/map_types/__init__.py
pynspd/map_types/_autogen_layers.py
pynspd/map_types/enums.py
pynspd/schemas/__init__.py
pynspd/schemas/_autogen_features.py
pynspd/schemas/_common.py
pynspd/schemas/base_feature.py
pynspd/schemas/feature.py
pynspd/schemas/geometries.py
pynspd/schemas/layer_configs.py
pynspd/schemas/properties.py
pynspd/schemas/responses.py
pynspd-1.1.11.dist-info/METADATA
pynspd-1.1.11.dist-info/WHEEL
pynspd-1.1.11.dist-info/entry_points.txt
pynspd-1.1.11.dist-info/licenses/LICENSE
pynspd-1.1.11.dist-info/RECORD
