Metadata-Version: 2.4
Name: pynspd
Version: 1.1.11
Summary: Python-библиотека для работы с https://nspd.gov.ru (ex-ПКК)
Project-URL: Homepage, https://yazmolod.github.io/pynspd/
Project-URL: Repository, https://github.com/yazmolod/pynspd
Project-URL: Issues, https://github.com/yazmolod/pynspd/issues
Project-URL: Changelog, https://github.com/yazmolod/pynspd/releases
Author-email: Aleksandr Litovchenko <yazmolod@gmail.com>
License: MIT License
License-File: LICENSE
Classifier: License :: OSI Approved :: MIT License
Classifier: Programming Language :: Python :: 3
Classifier: Programming Language :: Python :: 3.10
Classifier: Programming Language :: Python :: 3.11
Classifier: Programming Language :: Python :: 3.12
Classifier: Programming Language :: Python :: 3.13
Requires-Python: >=3.10
Requires-Dist: geojson-pydantic>=1.2.0
Requires-Dist: hishel<1.0.0,>=0.1.1
Requires-Dist: httpx>=0.28.1
Requires-Dist: mercantile>=1.2.1
Requires-Dist: numpy>1.24.4
Requires-Dist: pydantic>=2.10.4
Requires-Dist: pyproj>=3.7
Requires-Dist: shapely>=2.0.6
Requires-Dist: ua-generator>=2.0.10
Provides-Extra: cli
Requires-Dist: geopandas>=1.0.1; extra == 'cli'
Requires-Dist: openpyxl>=3.1.5; extra == 'cli'
Requires-Dist: questionary>=2.1.0; extra == 'cli'
Requires-Dist: typer>=0.15.2; extra == 'cli'
Provides-Extra: redis
Requires-Dist: redis==6.0.0; extra == 'redis'
Provides-Extra: socks
Requires-Dist: socksio>=1.0.0; extra == 'socks'
Provides-Extra: sqlite
Requires-Dist: anysqlite>=0.0.5; extra == 'sqlite'
